ap_python_sdk-0.1.3.dist-info/METADATA
ap_python_sdk-0.1.3.dist-info/DESCRIPTION.rst
ap_python_sdk-0.1.3.dist-info/RECORD
ap_python_sdk-0.1.3.dist-info/top_level.txt
ap_python_sdk-0.1.3.dist-info/metadata.json
ap_python_sdk-0.1.3.dist-info/WHEEL
ap_python_sdk/resources.py
ap_python_sdk/version.py
ap_python_sdk/util.py
ap_python_sdk/http_client.py
ap_python_sdk/api_requester.py
ap_python_sdk/error.py
ap_python_sdk/__init__.py
