Metadata-Version: 2.0
Name: ap-python-sdk
Version: 0.1.3
Summary: SDK for python application to use Alternative Payments
Home-page: https://github.com/AlternativePayments/ap-python-sdk
Author: Marjan Stojanovic
Author-email: marjan.stojanovic90@gmail.com
License: MIT
Keywords: alternative payments python sdk development
Platform: UNKNOWN
Classifier: Development Status :: 5 - Production/Stable
Classifier: Intended Audience :: Developers
Classifier: Topic :: Software Development :: Libraries :: Python Modules
Classifier: License :: OSI Approved :: MIT License
Classifier: Programming Language :: Python :: 2.7
Requires-Dist: requests (>=0.8.8)
